hatiyar/__init__.py
hatiyar/__main__.py
hatiyar/main.py
hatiyar/cli/commands.py
hatiyar/cli/shell.py
hatiyar/core/config.py
hatiyar/core/module_base.py
hatiyar/core/modules.py
hatiyar/modules/__init__.py
hatiyar/modules/cloud/__init__.py
hatiyar/modules/cloud/cloud.yaml
hatiyar/modules/cloud/aws/__init__.py
hatiyar/modules/cloud/aws/amplify.py
hatiyar/modules/cloud/aws/aws.yaml
hatiyar/modules/cloud/aws/container.py
hatiyar/modules/cloud/aws/database.py
hatiyar/modules/cloud/aws/ec2.py
hatiyar/modules/cloud/aws/iam.py
hatiyar/modules/cloud/aws/lambda.py
hatiyar/modules/cloud/aws/route53.py
hatiyar/modules/cloud/aws/s3.py
hatiyar/modules/cloud/aws/secrets.py
hatiyar/modules/cloud/azure/__init__.py
hatiyar/modules/cloud/gcp/__init__.py
hatiyar/modules/cve/__init__.py
hatiyar/modules/cve/cve.yaml
hatiyar/modules/cve/cve_2021_42013.py
hatiyar/modules/cve/cve_2021_43798.py
hatiyar/modules/enumeration/__init__.py
hatiyar/modules/enumeration/enumeration.yaml
hatiyar/modules/misc/__init__.py
hatiyar/modules/misc/hello_world.py
hatiyar/modules/misc/misc.yaml
hatiyar/modules/platforms/__init__.py
hatiyar/modules/platforms/platforms.yaml
hatiyar/web/__init__.py
hatiyar/web/config.py
hatiyar/web/main.py
hatiyar/web/routes.py
hatiyar-1.1.0.dist-info/licenses/LICENSE
hatiyar-1.1.0.dist-info/METADATA
hatiyar-1.1.0.dist-info/WHEEL
hatiyar-1.1.0.dist-info/entry_points.txt
hatiyar-1.1.0.dist-info/top_level.txt
hatiyar-1.1.0.dist-info/RECORD
