Metadata-Version: 2.4
Name: hatiyar
Version: 1.1.0
Summary: security toolkit designed for penetration testing, vulnerability assessment, and security research.
Requires-Python: >=3.9
License-File: LICENSE
Requires-Dist: boto3>=1.7.84
Requires-Dist: boto3-stubs>=1.40.59
Requires-Dist: fastapi>=0.119.1
Requires-Dist: jinja2>=3.1.6
Requires-Dist: pluggy>=1.6.0
Requires-Dist: prompt-toolkit>=3.0.52
Requires-Dist: pydantic>=2.12.0
Requires-Dist: pyyaml>=6.0.1
Requires-Dist: requests>=2.32.0
Requires-Dist: rich>=14.2.0
Requires-Dist: typer>=0.12.0
Requires-Dist: uvicorn>=0.38.0
Provides-Extra: dev
Requires-Dist: mypy>=1.18.2; extra == "dev"
Requires-Dist: pre-commit>=4.3.0; extra == "dev"
Requires-Dist: pytest>=8.4.2; extra == "dev"
Requires-Dist: python-semantic-release>=9.14.0; extra == "dev"
Requires-Dist: types-pyyaml>=6.0.12.20250915; extra == "dev"
Requires-Dist: types-requests>=2.32.4.20250913; extra == "dev"
Requires-Dist: ruff>=0.8.0; extra == "dev"
Dynamic: license-file
